{
  "stats": {
    "suites": 1,
    "tests": 6,
    "passes": 6,
    "pending": 0,
    "failures": 0,
    "start": "2023-06-30T11:48:29.077Z",
    "end": "2023-06-30T11:52:21.691Z",
    "duration": 232614,
    "testsRegistered": 6,
    "passPercent": 100,
    "pendingPercent": 0,
    "other": 0,
    "hasOther": false,
    "skipped": 0,
    "hasSkipped": false
  },
  "results": [
    {
      "uuid": "2ab7a92d-6855-4142-b2e1-fb43a3c1abac",
      "title": "",
      "fullFile": "D:\\allproject\\alkademik\\research-unit-test-bacatarot\\test\\app\\dashboard\\index.js",
      "file": "\\test\\app\\dashboard\\index.js",
      "beforeHooks": [],
      "afterHooks": [],
      "tests": [],
      "suites": [
        {
          "uuid": "4c99c14b-ec02-4c2c-8308-69084711f7de",
          "title": "Dashboard",
          "fullFile": "D:\\allproject\\alkademik\\research-unit-test-bacatarot\\test\\app\\dashboard\\index.js",
          "file": "\\test\\app\\dashboard\\index.js",
          "beforeHooks": [],
          "afterHooks": [
            {
              "title": "\"after all\" hook in \"Dashboard\"",
              "fullTitle": "Dashboard \"after all\" hook in \"Dashboard\"",
              "timedOut": false,
              "duration": 1,
              "state": null,
              "speed": null,
              "pass": false,
              "fail": false,
              "pending": false,
              "context": null,
              "code": "",
              "err": {},
              "uuid": "f72e5aeb-e1c9-4586-a66b-ff7747cd5920",
              "parentUUID": "4c99c14b-ec02-4c2c-8308-69084711f7de",
              "isHook": true,
              "skipped": false
            },
            {
              "title": "\"after each\" hook in \"Dashboard\"",
              "fullTitle": "Dashboard \"after each\" hook in \"Dashboard\"",
              "timedOut": false,
              "duration": 3363,
              "state": null,
              "speed": null,
              "pass": false,
              "fail": false,
              "pending": false,
              "context": null,
              "code": "",
              "err": {},
              "uuid": "1402879f-f723-41dd-8fa0-bbc25cb91445",
              "parentUUID": "4c99c14b-ec02-4c2c-8308-69084711f7de",
              "isHook": true,
              "skipped": false
            }
          ],
          "tests": [
            {
              "title": "User - Search of reader on home page dashboard from browser firefox",
              "fullTitle": "Dashboard User - Search of reader on home page dashboard from browser firefox",
              "timedOut": false,
              "duration": 37707,
              "state": "passed",
              "speed": "slow",
              "pass": true,
              "fail": false,
              "pending": false,
              "context": "[\n  {\n    \"title\": \"Expected Results\",\n    \"value\": \"- Successfully got the results search of reader ✅\"\n  },\n  {\n    \"title\": \"Performance Results\",\n    \"value\": \"Friday, June 30, 2023 6:49:06 PM\\n(Durasi waktu navigasi: 28 seconds)   \\n=====================================================================\\nWaktu Permintaan Pertama (fetchStart): (0) milliseconds ( 0 seconds )\\nWaktu Pencarian Nama Domain Dimulai (domainLookupStart): (8) milliseconds ( 0.008 seconds )\\nWaktu Pencarian Nama Domain Selesai (domainLookupEnd): (9) milliseconds ( 0.009 seconds )\\nWaktu Permintaan Dimulai (requestStart): (10) milliseconds ( 0.01 seconds )\\n=====================================================================\\nWaktu Respons Dimulai (responseStart): (11) milliseconds ( 0.011 seconds )\\nWaktu Respons Selesai (responseEnd): (11) milliseconds ( 0.011 seconds )\\nWaktu Memuat Dokumen (domLoading): (367) milliseconds ( 0.367 seconds )\\n=====================================================================\\nWaktu Event Unload Dimulai (unloadEventStart): (-1688125712008) milliseconds ( -1688125712.008 seconds )\\nWaktu Event Unload Selesai (unloadEventEnd): (-1688125712008) milliseconds ( -1688125712.008 seconds )\\n=====================================================================\\nWaktu Interaktif DOM (domInteractive): (1494) milliseconds ( 1.494 seconds )\\nWaktu Event DOMContentLoaded Dimulai (domContentLoadedEventStart): (1522) milliseconds ( 1.522 seconds )\\nWaktu Event DOMContentLoaded Selesai (domContentLoadedEventEnd): (1531) milliseconds ( 1.531 seconds )\\n=====================================================================\\nWaktu Dokumen Selesai Dimuat (domComplete): (1558) milliseconds ( 1.558 seconds )\\nWaktu Event Load Dimulai (loadEventStart): (1558) milliseconds ( 1.558 seconds )\\n=====================================================================\\n(timestamp loadEventEnd: 1688125713566)\\nWaktu Event Load Selesai (loadEventEnd): (1558) milliseconds ( 1.558 seconds )\\n            \"\n  },\n  {\n    \"title\": \"Screenshoot-Test-Results\",\n    \"value\": \"..\\\\..\\\\..\\\\..\\\\..\\\\testResults\\\\screenshoots\\\\app\\\\dashboard\\\\index\\\\1-[passed]-2023-06-30_18-49-06.png\"\n  }\n]",
              "code": "",
              "err": {},
              "uuid": "a9e68d30-0da4-4147-b3d4-beed7ad28039",
              "parentUUID": "4c99c14b-ec02-4c2c-8308-69084711f7de",
              "isHook": false,
              "skipped": false
            },
            {
              "title": "Reader - Turn on the schedule per day of consultation from browser firefox",
              "fullTitle": "Dashboard Reader - Turn on the schedule per day of consultation from browser firefox",
              "timedOut": false,
              "duration": 34866,
              "state": "passed",
              "speed": "slow",
              "pass": true,
              "fail": false,
              "pending": false,
              "context": "[\n  {\n    \"title\": \"Expected Results\",\n    \"value\": \"- Successfully turn on the schedule per day ✅\"\n  },\n  {\n    \"title\": \"Performance Results\",\n    \"value\": \"Friday, June 30, 2023 6:49:45 PM\\n(Durasi waktu navigasi: 46 seconds)   \\n=====================================================================\\nWaktu Permintaan Pertama (fetchStart): (0) milliseconds ( 0 seconds )\\nWaktu Pencarian Nama Domain Dimulai (domainLookupStart): (10) milliseconds ( 0.01 seconds )\\nWaktu Pencarian Nama Domain Selesai (domainLookupEnd): (10) milliseconds ( 0.01 seconds )\\nWaktu Permintaan Dimulai (requestStart): (12) milliseconds ( 0.012 seconds )\\n=====================================================================\\nWaktu Respons Dimulai (responseStart): (13) milliseconds ( 0.013 seconds )\\nWaktu Respons Selesai (responseEnd): (13) milliseconds ( 0.013 seconds )\\nWaktu Memuat Dokumen (domLoading): (239) milliseconds ( 0.239 seconds )\\n=====================================================================\\nWaktu Event Unload Dimulai (unloadEventStart): (-1688125753366) milliseconds ( -1688125753.366 seconds )\\nWaktu Event Unload Selesai (unloadEventEnd): (-1688125753366) milliseconds ( -1688125753.366 seconds )\\n=====================================================================\\nWaktu Interaktif DOM (domInteractive): (1243) milliseconds ( 1.243 seconds )\\nWaktu Event DOMContentLoaded Dimulai (domContentLoadedEventStart): (1273) milliseconds ( 1.273 seconds )\\nWaktu Event DOMContentLoaded Selesai (domContentLoadedEventEnd): (1277) milliseconds ( 1.277 seconds )\\n=====================================================================\\nWaktu Dokumen Selesai Dimuat (domComplete): (1305) milliseconds ( 1.305 seconds )\\nWaktu Event Load Dimulai (loadEventStart): (1305) milliseconds ( 1.305 seconds )\\n=====================================================================\\n(timestamp loadEventEnd: 1688125754672)\\nWaktu Event Load Selesai (loadEventEnd): (1306) milliseconds ( 1.306 seconds )\\n            \"\n  },\n  {\n    \"title\": \"Screenshoot-Test-Results\",\n    \"value\": \"..\\\\..\\\\..\\\\..\\\\..\\\\testResults\\\\screenshoots\\\\app\\\\dashboard\\\\index\\\\2-[passed]-2023-06-30_18-49-45.png\"\n  }\n]",
              "code": "",
              "err": {},
              "uuid": "54ec1bcf-f81b-4d93-bf59-da4f4f53f9ce",
              "parentUUID": "4c99c14b-ec02-4c2c-8308-69084711f7de",
              "isHook": false,
              "skipped": false
            },
            {
              "title": "Reader - Turn off the schedule per day of consultation from browser firefox",
              "fullTitle": "Dashboard Reader - Turn off the schedule per day of consultation from browser firefox",
              "timedOut": false,
              "duration": 36448,
              "state": "passed",
              "speed": "slow",
              "pass": true,
              "fail": false,
              "pending": false,
              "context": "[\n  {\n    \"title\": \"Expected Results\",\n    \"value\": \"- Successfully turn off the schedule per day ✅\"\n  },\n  {\n    \"title\": \"Performance Results\",\n    \"value\": \"Friday, June 30, 2023 6:50:26 PM\\n(Durasi waktu navigasi: 9 seconds)   \\n=====================================================================\\nWaktu Permintaan Pertama (fetchStart): (0) milliseconds ( 0 seconds )\\nWaktu Pencarian Nama Domain Dimulai (domainLookupStart): (8) milliseconds ( 0.008 seconds )\\nWaktu Pencarian Nama Domain Selesai (domainLookupEnd): (9) milliseconds ( 0.009 seconds )\\nWaktu Permintaan Dimulai (requestStart): (9) milliseconds ( 0.009 seconds )\\n=====================================================================\\nWaktu Respons Dimulai (responseStart): (11) milliseconds ( 0.011 seconds )\\nWaktu Respons Selesai (responseEnd): (11) milliseconds ( 0.011 seconds )\\nWaktu Memuat Dokumen (domLoading): (343) milliseconds ( 0.343 seconds )\\n=====================================================================\\nWaktu Event Unload Dimulai (unloadEventStart): (-1688125792509) milliseconds ( -1688125792.509 seconds )\\nWaktu Event Unload Selesai (unloadEventEnd): (-1688125792509) milliseconds ( -1688125792.509 seconds )\\n=====================================================================\\nWaktu Interaktif DOM (domInteractive): (1754) milliseconds ( 1.754 seconds )\\nWaktu Event DOMContentLoaded Dimulai (domContentLoadedEventStart): (1778) milliseconds ( 1.778 seconds )\\nWaktu Event DOMContentLoaded Selesai (domContentLoadedEventEnd): (1782) milliseconds ( 1.782 seconds )\\n=====================================================================\\nWaktu Dokumen Selesai Dimuat (domComplete): (1810) milliseconds ( 1.81 seconds )\\nWaktu Event Load Dimulai (loadEventStart): (1810) milliseconds ( 1.81 seconds )\\n=====================================================================\\n(timestamp loadEventEnd: 1688125794319)\\nWaktu Event Load Selesai (loadEventEnd): (1810) milliseconds ( 1.81 seconds )\\n            \"\n  },\n  {\n    \"title\": \"Screenshoot-Test-Results\",\n    \"value\": \"..\\\\..\\\\..\\\\..\\\\..\\\\testResults\\\\screenshoots\\\\app\\\\dashboard\\\\index\\\\3-[passed]-2023-06-30_18-50-26.png\"\n  }\n]",
              "code": "",
              "err": {},
              "uuid": "120a7b09-efc5-4d24-8488-1625654a8fb3",
              "parentUUID": "4c99c14b-ec02-4c2c-8308-69084711f7de",
              "isHook": false,
              "skipped": false
            },
            {
              "title": "User - Search of reader on home page dashboard from browser chrome",
              "fullTitle": "Dashboard User - Search of reader on home page dashboard from browser chrome",
              "timedOut": false,
              "duration": 35922,
              "state": "passed",
              "speed": "slow",
              "pass": true,
              "fail": false,
              "pending": false,
              "context": "[\n  {\n    \"title\": \"Expected Results\",\n    \"value\": \"- Successfully got the results search of reader ✅\"\n  },\n  {\n    \"title\": \"Performance Results\",\n    \"value\": \"Friday, June 30, 2023 6:51:06 PM\\n(Durasi waktu navigasi: 22 seconds)   \\n=====================================================================\\nWaktu Permintaan Pertama (fetchStart): (4) milliseconds ( 0.004 seconds )\\nWaktu Pencarian Nama Domain Dimulai (domainLookupStart): (4) milliseconds ( 0.004 seconds )\\nWaktu Pencarian Nama Domain Selesai (domainLookupEnd): (4) milliseconds ( 0.004 seconds )\\nWaktu Permintaan Dimulai (requestStart): (12) milliseconds ( 0.012 seconds )\\n=====================================================================\\nWaktu Respons Dimulai (responseStart): (15) milliseconds ( 0.015 seconds )\\nWaktu Respons Selesai (responseEnd): (19) milliseconds ( 0.019 seconds )\\nWaktu Memuat Dokumen (domLoading): (26) milliseconds ( 0.026 seconds )\\n=====================================================================\\nWaktu Event Unload Dimulai (unloadEventStart): (-1688125831342) milliseconds ( -1688125831.342 seconds )\\nWaktu Event Unload Selesai (unloadEventEnd): (-1688125831342) milliseconds ( -1688125831.342 seconds )\\n=====================================================================\\nWaktu Interaktif DOM (domInteractive): (2134) milliseconds ( 2.134 seconds )\\nWaktu Event DOMContentLoaded Dimulai (domContentLoadedEventStart): (2134) milliseconds ( 2.134 seconds )\\nWaktu Event DOMContentLoaded Selesai (domContentLoadedEventEnd): (2134) milliseconds ( 2.134 seconds )\\n=====================================================================\\nWaktu Dokumen Selesai Dimuat (domComplete): (2156) milliseconds ( 2.156 seconds )\\nWaktu Event Load Dimulai (loadEventStart): (2156) milliseconds ( 2.156 seconds )\\n=====================================================================\\n(timestamp loadEventEnd: 1688125833498)\\nWaktu Event Load Selesai (loadEventEnd): (2156) milliseconds ( 2.156 seconds )\\n            \"\n  },\n  {\n    \"title\": \"Screenshoot-Test-Results\",\n    \"value\": \"..\\\\..\\\\..\\\\..\\\\..\\\\testResults\\\\screenshoots\\\\app\\\\dashboard\\\\index\\\\4-[passed]-2023-06-30_18-51-06.png\"\n  }\n]",
              "code": "",
              "err": {},
              "uuid": "1944438e-72aa-4fd9-896f-54ffed92c109",
              "parentUUID": "4c99c14b-ec02-4c2c-8308-69084711f7de",
              "isHook": false,
              "skipped": false
            },
            {
              "title": "Reader - Turn on the schedule per day of consultation from browser chrome",
              "fullTitle": "Dashboard Reader - Turn on the schedule per day of consultation from browser chrome",
              "timedOut": false,
              "duration": 32069,
              "state": "passed",
              "speed": "slow",
              "pass": true,
              "fail": false,
              "pending": false,
              "context": "[\n  {\n    \"title\": \"Expected Results\",\n    \"value\": \"- Successfully turn on the schedule per day ✅\"\n  },\n  {\n    \"title\": \"Performance Results\",\n    \"value\": \"Friday, June 30, 2023 6:51:42 PM\\n(Durasi waktu navigasi: 24 seconds)   \\n=====================================================================\\nWaktu Permintaan Pertama (fetchStart): (4) milliseconds ( 0.004 seconds )\\nWaktu Pencarian Nama Domain Dimulai (domainLookupStart): (4) milliseconds ( 0.004 seconds )\\nWaktu Pencarian Nama Domain Selesai (domainLookupEnd): (4) milliseconds ( 0.004 seconds )\\nWaktu Permintaan Dimulai (requestStart): (13) milliseconds ( 0.013 seconds )\\n=====================================================================\\nWaktu Respons Dimulai (responseStart): (14) milliseconds ( 0.014 seconds )\\nWaktu Respons Selesai (responseEnd): (21) milliseconds ( 0.021 seconds )\\nWaktu Memuat Dokumen (domLoading): (21) milliseconds ( 0.021 seconds )\\n=====================================================================\\nWaktu Event Unload Dimulai (unloadEventStart): (-1688125870584) milliseconds ( -1688125870.584 seconds )\\nWaktu Event Unload Selesai (unloadEventEnd): (-1688125870584) milliseconds ( -1688125870.584 seconds )\\n=====================================================================\\nWaktu Interaktif DOM (domInteractive): (774) milliseconds ( 0.774 seconds )\\nWaktu Event DOMContentLoaded Dimulai (domContentLoadedEventStart): (774) milliseconds ( 0.774 seconds )\\nWaktu Event DOMContentLoaded Selesai (domContentLoadedEventEnd): (774) milliseconds ( 0.774 seconds )\\n=====================================================================\\nWaktu Dokumen Selesai Dimuat (domComplete): (793) milliseconds ( 0.793 seconds )\\nWaktu Event Load Dimulai (loadEventStart): (793) milliseconds ( 0.793 seconds )\\n=====================================================================\\n(timestamp loadEventEnd: 1688125871377)\\nWaktu Event Load Selesai (loadEventEnd): (793) milliseconds ( 0.793 seconds )\\n            \"\n  },\n  {\n    \"title\": \"Screenshoot-Test-Results\",\n    \"value\": \"..\\\\..\\\\..\\\\..\\\\..\\\\testResults\\\\screenshoots\\\\app\\\\dashboard\\\\index\\\\5-[passed]-2023-06-30_18-51-41.png\"\n  }\n]",
              "code": "",
              "err": {},
              "uuid": "ba95e990-90a4-439b-a928-9219644808c1",
              "parentUUID": "4c99c14b-ec02-4c2c-8308-69084711f7de",
              "isHook": false,
              "skipped": false
            },
            {
              "title": "Reader - Turn off the schedule per day of consultation from browser chrome",
              "fullTitle": "Dashboard Reader - Turn off the schedule per day of consultation from browser chrome",
              "timedOut": false,
              "duration": 33158,
              "state": "passed",
              "speed": "slow",
              "pass": true,
              "fail": false,
              "pending": false,
              "context": "[\n  {\n    \"title\": \"Expected Results\",\n    \"value\": \"- Successfully turn off the schedule per day ✅\"\n  },\n  {\n    \"title\": \"Performance Results\",\n    \"value\": \"Friday, June 30, 2023 6:52:18 PM\\n(Durasi waktu navigasi: 26 seconds)   \\n=====================================================================\\nWaktu Permintaan Pertama (fetchStart): (1) milliseconds ( 0.001 seconds )\\nWaktu Pencarian Nama Domain Dimulai (domainLookupStart): (1) milliseconds ( 0.001 seconds )\\nWaktu Pencarian Nama Domain Selesai (domainLookupEnd): (1) milliseconds ( 0.001 seconds )\\nWaktu Permintaan Dimulai (requestStart): (13) milliseconds ( 0.013 seconds )\\n=====================================================================\\nWaktu Respons Dimulai (responseStart): (14) milliseconds ( 0.014 seconds )\\nWaktu Respons Selesai (responseEnd): (14) milliseconds ( 0.014 seconds )\\nWaktu Memuat Dokumen (domLoading): (18) milliseconds ( 0.018 seconds )\\n=====================================================================\\nWaktu Event Unload Dimulai (unloadEventStart): (-1688125905926) milliseconds ( -1688125905.926 seconds )\\nWaktu Event Unload Selesai (unloadEventEnd): (-1688125905926) milliseconds ( -1688125905.926 seconds )\\n=====================================================================\\nWaktu Interaktif DOM (domInteractive): (789) milliseconds ( 0.789 seconds )\\nWaktu Event DOMContentLoaded Dimulai (domContentLoadedEventStart): (789) milliseconds ( 0.789 seconds )\\nWaktu Event DOMContentLoaded Selesai (domContentLoadedEventEnd): (789) milliseconds ( 0.789 seconds )\\n=====================================================================\\nWaktu Dokumen Selesai Dimuat (domComplete): (812) milliseconds ( 0.812 seconds )\\nWaktu Event Load Dimulai (loadEventStart): (812) milliseconds ( 0.812 seconds )\\n=====================================================================\\n(timestamp loadEventEnd: 1688125906738)\\nWaktu Event Load Selesai (loadEventEnd): (812) milliseconds ( 0.812 seconds )\\n            \"\n  },\n  {\n    \"title\": \"Screenshoot-Test-Results\",\n    \"value\": \"..\\\\..\\\\..\\\\..\\\\..\\\\testResults\\\\screenshoots\\\\app\\\\dashboard\\\\index\\\\6-[passed]-2023-06-30_18-52-18.png\"\n  }\n]",
              "code": "",
              "err": {},
              "uuid": "e07e5dd5-0764-45de-807e-defeb4f87e73",
              "parentUUID": "4c99c14b-ec02-4c2c-8308-69084711f7de",
              "isHook": false,
              "skipped": false
            }
          ],
          "suites": [],
          "passes": [
            "a9e68d30-0da4-4147-b3d4-beed7ad28039",
            "54ec1bcf-f81b-4d93-bf59-da4f4f53f9ce",
            "120a7b09-efc5-4d24-8488-1625654a8fb3",
            "1944438e-72aa-4fd9-896f-54ffed92c109",
            "ba95e990-90a4-439b-a928-9219644808c1",
            "e07e5dd5-0764-45de-807e-defeb4f87e73"
          ],
          "failures": [],
          "pending": [],
          "skipped": [],
          "duration": 210170,
          "root": false,
          "rootEmpty": false,
          "_timeout": 0
        }
      ],
      "passes": [],
      "failures": [],
      "pending": [],
      "skipped": [],
      "duration": 0,
      "root": true,
      "rootEmpty": true,
      "_timeout": 0
    }
  ],
  "meta": {
    "mocha": {
      "version": "10.2.0"
    },
    "mochawesome": {
      "options": {
        "quiet": false,
        "reportFilename": "app/dashboard/[status]-index-report",
        "saveHtml": true,
        "saveJson": true,
        "consoleReporter": "spec",
        "useInlineDiffs": false,
        "code": false
      },
      "version": "7.1.3"
    },
    "marge": {
      "options": {
        "code": "false",
        "cdn": "true",
        "charts": "true",
        "reportDir": "testResults/reports",
        "reportFilename": "app/dashboard/[status]-index-report",
        "reportPageTitle": "Laporan-Harian-Testing"
      },
      "version": "6.2.0"
    }
  }
}